stv_path_converter/__init__.py
stv_path_converter/main.py
stv_path_converter/core/__init__.py
stv_path_converter/core/converter.py
stv_path_converter/core/stv_parse.py
stv_path_converter/text/__init__.py
stv_path_converter/text/change_text.py
stv_path_converter/utils/__init__.py
stv_path_converter/utils/head.py
stv_path_converter/utils/lic.py
stv_path_converter-0.0.1.dist-info/METADATA
stv_path_converter-0.0.1.dist-info/WHEEL
stv_path_converter-0.0.1.dist-info/entry_points.txt
stv_path_converter-0.0.1.dist-info/top_level.txt
stv_path_converter-0.0.1.dist-info/RECORD
