Metadata-Version: 2.4
Name: stv_path_converter
Version: 0.0.1
Summary: Linux to Windows Path or Windows to Linux path converter
Author-email: "星灿长风v(StarWindv)" <starwindv.stv@gmail.com>
License: MIT
Project-URL: Homepage, https://github.com/StarWindv/win-linux-path_converter
Classifier: Programming Language :: Python :: 3
Requires-Python: >=3.6
Requires-Dist: stv_utils
